jsonapihelper/__init__.py
jsonapihelper-1.0.dist-info/DESCRIPTION.rst
jsonapihelper-1.0.dist-info/METADATA
jsonapihelper-1.0.dist-info/RECORD
jsonapihelper-1.0.dist-info/WHEEL
jsonapihelper-1.0.dist-info/metadata.json
jsonapihelper-1.0.dist-info/top_level.txt
